[{"id ROM": "1-1-1", "marca": "SanDisk", "capacidad": "250 GB", "tipo": "HDD", "instancias": "ROM\\1\\1\\1\\"}, {"id ROM": "1-1-2", "marca": "SanDisk", "capacidad": "250 GB", "tipo": "SSD", "instancias": "ROM\\1\\1\\2\\"}, {"id ROM": "1-1-3", "marca": "SanDisk", "capacidad": "250 GB", "tipo": "NVME M.2", "instancias": "ROM\\1\\1\\3\\"}, {"id ROM": "1-2-1", "marca": "SanDisk", "capacidad": "500 GB", "tipo": "HDD", "instancias": "ROM\\1\\2\\1\\"}, {"id ROM": "1-2-2", "marca": "SanDisk", "capacidad": "500 GB", "tipo": "SSD", "instancias": "ROM\\1\\2\\2\\"}, {"id ROM": "1-2-3", "marca": "SanDisk", "capacidad": "500 GB", "tipo": "NVME M.2", "instancias": "ROM\\1\\2\\3\\"}, {"id ROM": "1-3-1", "marca": "SanDisk", "capacidad": "1 TB", "tipo": "HDD", "instancias": "ROM\\1\\3\\1\\"}, {"id ROM": "1-3-2", "marca": "SanDisk", "capacidad": "1 TB", "tipo": "SSD", "instancias": "ROM\\1\\3\\2\\"}, {"id ROM": "1-3-3", "marca": "SanDisk", "capacidad": "1 TB", "tipo": "NVME M.2", "instancias": "ROM\\1\\3\\3\\"}, {"id ROM": "1-4-1", "marca": "SanDisk", "capacidad": "2TB", "tipo": "HDD", "instancias": "ROM\\1\\4\\1\\"}, {"id ROM": "1-4-2", "marca": "SanDisk", "capacidad": "2TB", "tipo": "SSD", "instancias": "ROM\\1\\4\\2\\"}, {"id ROM": "1-4-3", "marca": "SanDisk", "capacidad": "2TB", "tipo": "NVME M.2", "instancias": "ROM\\1\\4\\3\\"}, {"id ROM": "1-5-1", "marca": "SanDisk", "capacidad": "4 TB", "tipo": "HDD", "instancias": "ROM\\1\\5\\1\\"}, {"id ROM": "1-5-2", "marca": "SanDisk", "capacidad": "4 TB", "tipo": "SSD", "instancias": "ROM\\1\\5\\2\\"}, {"id ROM": "1-5-3", "marca": "SanDisk", "capacidad": "4 TB", "tipo": "NVME M.2", "instancias": "ROM\\1\\5\\3\\"}, {"id ROM": "2-1-1", "marca": "Kingston", "capacidad": "250 GB", "tipo": "HDD", "instancias": "ROM\\2\\1\\1\\"}, {"id ROM": "2-1-2", "marca": "Kingston", "capacidad": "250 GB", "tipo": "SSD", "instancias": "ROM\\2\\1\\2\\"}, {"id ROM": "2-1-3", "marca": "Kingston", "capacidad": "250 GB", "tipo": "NVME M.2", "instancias": "ROM\\2\\1\\3\\"}, {"id ROM": "2-2-1", "marca": "Kingston", "capacidad": "500 GB", "tipo": "HDD", "instancias": "ROM\\2\\2\\1\\"}, {"id ROM": "2-2-2", "marca": "Kingston", "capacidad": "500 GB", "tipo": "SSD", "instancias": "ROM\\2\\2\\2\\"}, {"id ROM": "2-2-3", "marca": "Kingston", "capacidad": "500 GB", "tipo": "NVME M.2", "instancias": "ROM\\2\\2\\3\\"}, {"id ROM": "2-3-1", "marca": "Kingston", "capacidad": "1 TB", "tipo": "HDD", "instancias": "ROM\\2\\3\\1\\"}, {"id ROM": "2-3-2", "marca": "Kingston", "capacidad": "1 TB", "tipo": "SSD", "instancias": "ROM\\2\\3\\2\\"}, {"id ROM": "2-3-3", "marca": "Kingston", "capacidad": "1 TB", "tipo": "NVME M.2", "instancias": "ROM\\2\\3\\3\\"}, {"id ROM": "2-4-1", "marca": "Kingston", "capacidad": "2TB", "tipo": "HDD", "instancias": "ROM\\2\\4\\1\\"}, {"id ROM": "2-4-2", "marca": "Kingston", "capacidad": "2TB", "tipo": "SSD", "instancias": "ROM\\2\\4\\2\\"}, {"id ROM": "2-4-3", "marca": "Kingston", "capacidad": "2TB", "tipo": "NVME M.2", "instancias": "ROM\\2\\4\\3\\"}, {"id ROM": "2-5-1", "marca": "Kingston", "capacidad": "4 TB", "tipo": "HDD", "instancias": "ROM\\2\\5\\1\\"}, {"id ROM": "2-5-2", "marca": "Kingston", "capacidad": "4 TB", "tipo": "SSD", "instancias": "ROM\\2\\5\\2\\"}, {"id ROM": "2-5-3", "marca": "Kingston", "capacidad": "4 TB", "tipo": "NVME M.2", "instancias": "ROM\\2\\5\\3\\"}, {"id ROM": "3-1-1", "marca": "Samsung", "capacidad": "250 GB", "tipo": "HDD", "instancias": "ROM\\3\\1\\1\\"}, {"id ROM": "3-1-2", "marca": "Samsung", "capacidad": "250 GB", "tipo": "SSD", "instancias": "ROM\\3\\1\\2\\"}, {"id ROM": "3-1-3", "marca": "Samsung", "capacidad": "250 GB", "tipo": "NVME M.2", "instancias": "ROM\\3\\1\\3\\"}, {"id ROM": "3-2-1", "marca": "Samsung", "capacidad": "500 GB", "tipo": "HDD", "instancias": "ROM\\3\\2\\1\\"}, {"id ROM": "3-2-2", "marca": "Samsung", "capacidad": "500 GB", "tipo": "SSD", "instancias": "ROM\\3\\2\\2\\"}, {"id ROM": "3-2-3", "marca": "Samsung", "capacidad": "500 GB", "tipo": "NVME M.2", "instancias": "ROM\\3\\2\\3\\"}, {"id ROM": "3-3-1", "marca": "Samsung", "capacidad": "1 TB", "tipo": "HDD", "instancias": "ROM\\3\\3\\1\\"}, {"id ROM": "3-3-2", "marca": "Samsung", "capacidad": "1 TB", "tipo": "SSD", "instancias": "ROM\\3\\3\\2\\"}, {"id ROM": "3-3-3", "marca": "Samsung", "capacidad": "1 TB", "tipo": "NVME M.2", "instancias": "ROM\\3\\3\\3\\"}, {"id ROM": "3-4-1", "marca": "Samsung", "capacidad": "2TB", "tipo": "HDD", "instancias": "ROM\\3\\4\\1\\"}, {"id ROM": "3-4-2", "marca": "Samsung", "capacidad": "2TB", "tipo": "SSD", "instancias": "ROM\\3\\4\\2\\"}, {"id ROM": "3-4-3", "marca": "Samsung", "capacidad": "2TB", "tipo": "NVME M.2", "instancias": "ROM\\3\\4\\3\\"}, {"id ROM": "3-5-1", "marca": "Samsung", "capacidad": "4 TB", "tipo": "HDD", "instancias": "ROM\\3\\5\\1\\"}, {"id ROM": "3-5-2", "marca": "Samsung", "capacidad": "4 TB", "tipo": "SSD", "instancias": "ROM\\3\\5\\2\\"}, {"id ROM": "3-5-3", "marca": "Samsung", "capacidad": "4 TB", "tipo": "NVME M.2", "instancias": "ROM\\3\\5\\3\\"}, {"id ROM": "4-1-1", "marca": "Adata", "capacidad": "250 GB", "tipo": "HDD", "instancias": "ROM\\4\\1\\1\\"}, {"id ROM": "4-1-2", "marca": "Adata", "capacidad": "250 GB", "tipo": "SSD", "instancias": "ROM\\4\\1\\2\\"}, {"id ROM": "4-1-3", "marca": "Adata", "capacidad": "250 GB", "tipo": "NVME M.2", "instancias": "ROM\\4\\1\\3\\"}, {"id ROM": "4-2-1", "marca": "Adata", "capacidad": "500 GB", "tipo": "HDD", "instancias": "ROM\\4\\2\\1\\"}, {"id ROM": "4-2-2", "marca": "Adata", "capacidad": "500 GB", "tipo": "SSD", "instancias": "ROM\\4\\2\\2\\"}, {"id ROM": "4-2-3", "marca": "Adata", "capacidad": "500 GB", "tipo": "NVME M.2", "instancias": "ROM\\4\\2\\3\\"}, {"id ROM": "4-3-1", "marca": "Adata", "capacidad": "1 TB", "tipo": "HDD", "instancias": "ROM\\4\\3\\1\\"}, {"id ROM": "4-3-2", "marca": "Adata", "capacidad": "1 TB", "tipo": "SSD", "instancias": "ROM\\4\\3\\2\\"}, {"id ROM": "4-3-3", "marca": "Adata", "capacidad": "1 TB", "tipo": "NVME M.2", "instancias": "ROM\\4\\3\\3\\"}, {"id ROM": "4-4-1", "marca": "Adata", "capacidad": "2TB", "tipo": "HDD", "instancias": "ROM\\4\\4\\1\\"}, {"id ROM": "4-4-2", "marca": "Adata", "capacidad": "2TB", "tipo": "SSD", "instancias": "ROM\\4\\4\\2\\"}, {"id ROM": "4-4-3", "marca": "Adata", "capacidad": "2TB", "tipo": "NVME M.2", "instancias": "ROM\\4\\4\\3\\"}, {"id ROM": "4-5-1", "marca": "Adata", "capacidad": "4 TB", "tipo": "HDD", "instancias": "ROM\\4\\5\\1\\"}, {"id ROM": "4-5-2", "marca": "Adata", "capacidad": "4 TB", "tipo": "SSD", "instancias": "ROM\\4\\5\\2\\"}, {"id ROM": "4-5-3", "marca": "Adata", "capacidad": "4 TB", "tipo": "NVME M.2", "instancias": "ROM\\4\\5\\3\\"}, {"id ROM": "5-1-1", "marca": "Crucial", "capacidad": "250 GB", "tipo": "HDD", "instancias": "ROM\\5\\1\\1\\"}, {"id ROM": "5-1-2", "marca": "Crucial", "capacidad": "250 GB", "tipo": "SSD", "instancias": "ROM\\5\\1\\2\\"}, {"id ROM": "5-1-3", "marca": "Crucial", "capacidad": "250 GB", "tipo": "NVME M.2", "instancias": "ROM\\5\\1\\3\\"}, {"id ROM": "5-2-1", "marca": "Crucial", "capacidad": "500 GB", "tipo": "HDD", "instancias": "ROM\\5\\2\\1\\"}, {"id ROM": "5-2-2", "marca": "Crucial", "capacidad": "500 GB", "tipo": "SSD", "instancias": "ROM\\5\\2\\2\\"}, {"id ROM": "5-2-3", "marca": "Crucial", "capacidad": "500 GB", "tipo": "NVME M.2", "instancias": "ROM\\5\\2\\3\\"}, {"id ROM": "5-3-1", "marca": "Crucial", "capacidad": "1 TB", "tipo": "HDD", "instancias": "ROM\\5\\3\\1\\"}, {"id ROM": "5-3-2", "marca": "Crucial", "capacidad": "1 TB", "tipo": "SSD", "instancias": "ROM\\5\\3\\2\\"}, {"id ROM": "5-3-3", "marca": "Crucial", "capacidad": "1 TB", "tipo": "NVME M.2", "instancias": "ROM\\5\\3\\3\\"}, {"id ROM": "5-4-1", "marca": "Crucial", "capacidad": "2TB", "tipo": "HDD", "instancias": "ROM\\5\\4\\1\\"}, {"id ROM": "5-4-2", "marca": "Crucial", "capacidad": "2TB", "tipo": "SSD", "instancias": "ROM\\5\\4\\2\\"}, {"id ROM": "5-4-3", "marca": "Crucial", "capacidad": "2TB", "tipo": "NVME M.2", "instancias": "ROM\\5\\4\\3\\"}, {"id ROM": "5-5-1", "marca": "Crucial", "capacidad": "4 TB", "tipo": "HDD", "instancias": "ROM\\5\\5\\1\\"}, {"id ROM": "5-5-2", "marca": "Crucial", "capacidad": "4 TB", "tipo": "SSD", "instancias": "ROM\\5\\5\\2\\"}, {"id ROM": "5-5-3", "marca": "Crucial", "capacidad": "4 TB", "tipo": "NVME M.2", "instancias": "ROM\\5\\5\\3\\"}, {"id ROM": "6-1-1", "marca": "WD", "capacidad": "250 GB", "tipo": "HDD", "instancias": "ROM\\6\\1\\1\\"}, {"id ROM": "6-1-2", "marca": "WD", "capacidad": "250 GB", "tipo": "SSD", "instancias": "ROM\\6\\1\\2\\"}, {"id ROM": "6-1-3", "marca": "WD", "capacidad": "250 GB", "tipo": "NVME M.2", "instancias": "ROM\\6\\1\\3\\"}, {"id ROM": "6-2-1", "marca": "WD", "capacidad": "500 GB", "tipo": "HDD", "instancias": "ROM\\6\\2\\1\\"}, {"id ROM": "6-2-2", "marca": "WD", "capacidad": "500 GB", "tipo": "SSD", "instancias": "ROM\\6\\2\\2\\"}, {"id ROM": "6-2-3", "marca": "WD", "capacidad": "500 GB", "tipo": "NVME M.2", "instancias": "ROM\\6\\2\\3\\"}, {"id ROM": "6-3-1", "marca": "WD", "capacidad": "1 TB", "tipo": "HDD", "instancias": "ROM\\6\\3\\1\\"}, {"id ROM": "6-3-2", "marca": "WD", "capacidad": "1 TB", "tipo": "SSD", "instancias": "ROM\\6\\3\\2\\"}, {"id ROM": "6-3-3", "marca": "WD", "capacidad": "1 TB", "tipo": "NVME M.2", "instancias": "ROM\\6\\3\\3\\"}, {"id ROM": "6-4-1", "marca": "WD", "capacidad": "2TB", "tipo": "HDD", "instancias": "ROM\\6\\4\\1\\"}, {"id ROM": "6-4-2", "marca": "WD", "capacidad": "2TB", "tipo": "SSD", "instancias": "ROM\\6\\4\\2\\"}, {"id ROM": "6-4-3", "marca": "WD", "capacidad": "2TB", "tipo": "NVME M.2", "instancias": "ROM\\6\\4\\3\\"}, {"id ROM": "6-5-1", "marca": "WD", "capacidad": "4 TB", "tipo": "HDD", "instancias": "ROM\\6\\5\\1\\"}, {"id ROM": "6-5-2", "marca": "WD", "capacidad": "4 TB", "tipo": "SSD", "instancias": "ROM\\6\\5\\2\\"}, {"id ROM": "6-5-3", "marca": "WD", "capacidad": "4 TB", "tipo": "NVME M.2", "instancias": "ROM\\6\\5\\3\\"}]